Workbook

Sheet Comparison
B1: Portfolio | C1: URTH
A2: Return (5 year) | B2: =Portfolio!H1304/Portfolio!C1304 -> 0.59646313 | C2: =(URTH!G16/URTH!G1259)-1 -> 0.62816337
A3: Annualized Return | B3: =(1+B2)^(1/5) - 1 -> 0.09807443 | C3: =(1+C2)^(1/5) - 1 -> 0.10240099
A4: Volatility | B4: =_xlfn.STDEV.P(Portfolio!K3:K1304) * SQRT(252) -> 0.11256237 | C4: =_xlfn.STDEV.P(URTH!J2:J1258) * SQRT(252) -> 0.16167783
A5: Sharpe Ratio (rf = 4%) | B5: =(B3-0.04) / B4 -> 0.51593112 | C5: =(C3-0.04)/C4 -> 0.38595887
A6: Maximum Drawdown | B6: =MIN(Portfolio!N:N) -> -0.16515915 | C6: =MIN(URTH!M:M) -> -0.2605475

Sheet Portfolio
B1: date | C1: initial_capital | D1: investment_cost | E1: investment_value | F1: cash | G1: net_capital | H1: P&L | I1: percentage_change | K1: daily return | M1: peak | N1: daily drawdown
A2: 0 | B2: 44288 | C2: 1000000 | D2: 0 | E2: 0 | F2: 1000000 | G2: 1000000 | H2: 0 | I2: 0
A3: 1 | B3: 44291 | C3: 1000000 | D3: 906389.75 | E3: 905484.27 | F3: 93610.251 | G3: 999094.52 | H3: -905.4843 | I3: -0.000905 | K3: =(G3-G2) / G2 -> -0.0009054843 | M3: =MAX($G$2:G3) -> 1000000 | N3: =(G3-M3)/M3 -> -0.0009054843
A4: 2 | B4: 44292 | C4: 1000000 | D4: 976561.27 | E4: 978241.99 | F4: 23438.727 | G4: 1001680.7 | H4: 1680.7139 | I4: 0.001681 | K4: =(G4-G3) / G3 -> 0.0025885421 | M4: =MAX($G$2:G4) -> 1001680.7 | N4: =(G4-M4)/M4 -> 0
A5: 3 | B5: 44293 | C5: 1000000 | D5: 976561.27 | E5: 977199.72 | F5: 23438.727 | G5: 1000638.5 | H5: 638.4516 | I5: 0.000638 | K5: =(G5-G4) / G4 -> -0.0010405135 | M5: =MAX($G$2:G5) -> 1001680.7 | N5: =(G5-M5)/M5 -> -0.0010405135
A6: 4 | B6: 44294 | C6: 1000000 | D6: 976561.27 | E6: 977858.29 | F6: 23438.727 | G6: 1001297 | H6: 1297.0197 | I6: 0.001297 | K6: =(G6-G5) / G5 -> 0.0006581479 | M6: =MAX($G$2:G6) -> 1001680.7 | N6: =(G6-M6)/M6 -> -0.0003830504
A7: 5 | B7: 44295 | C7: 1000000 | D7: 976561.27 | E7: 981837.89 | F7: 23438.727 | G7: 1005276.6 | H7: 5276.6191 | I7: 0.005277 | K7: =(G7-G6) / G6 -> 0.0039744445 | M7: =MAX($G$2:G7) -> 1005276.6 | N7: =(G7-M7)/M7 -> 0
A8: 6 | B8: 44298 | C8: 1000000 | D8: 976561.27 | E8: 984757.66 | F8: 23438.727 | G8: 1008196.4 | H8: 8196.3879 | I8: 0.008196 | K8: =(G8-G7) / G7 -> 0.0029044432 | M8: =MAX($G$2:G8) -> 1008196.4 | N8: =(G8-M8)/M8 -> 0
A9: 7 | B9: 44299 | C9: 1000000 | D9: 976561.27 | E9: 987682.52 | F9: 23438.727 | G9: 1011121.2 | H9: 11121.248 | I9: 0.011121 | K9: =(G9-G8) / G8 -> 0.0029010818 | M9: =MAX($G$2:G9) -> 1011121.2 | N9: =(G9-M9)/M9 -> 0
A10: 8 | B10: 44300 | C10: 1000000 | D10: 976561.27 | E10: 988565.65 | F10: 23438.727 | G10: 1012004.4 | H10: 12004.375 | I10: 0.012004 | K10: =(G10-G9) / G9 -> 0.00087341306 | M10: =MAX($G$2:G10) -> 1012004.4 | N10: =(G10-M10)/M10 -> 0
A11: 9 | B11: 44301 | C11: 1000000 | D11: 976561.27 | E11: 998002.73 | F11: 23438.727 | G11: 1021441.5 | H11: 21441.455 | I11: 0.021441 | K11: =(G11-G10) / G10 -> 0.0093251383 | M11: =MAX($G$2:G11) -> 1021441.5 | N11: =(G11-M11)/M11 -> 0
A12: 10 | B12: 44302 | C12: 1000000 | D12: 976561.27 | E12: 1005214.2 | F12: 23438.727 | G12: 1028653 | H12: 28652.952 | I12: 0.028653 | K12: =(G12-G11) / G11 -> 0.0070601175 | M12: =MAX($G$2:G12) -> 1028653 | N12: =(G12-M12)/M12 -> 0
A13: 11 | B13: 44305 | C13: 1000000 | D13: 976561.27 | E13: 1003183 | F13: 23438.727 | G13: 1026621.7 | H13: 26621.715 | I13: 0.026622 | K13: =(G13-G12) / G12 -> -0.0019746575 | M13: =MAX($G$2:G13) -> 1028653 | N13: =(G13-M13)/M13 -> -0.0019746575
A14: 12 | B14: 44306 | C14: 1000000 | D14: 976561.27 | E14: 1003303.7 | F14: 23438.727 | G14: 1026742.4 | H14: 26742.416 | I14: 0.026742 | K14: =(G14-G13) / G13 -> 0.00011757076 | M14: =MAX($G$2:G14) -> 1028653 | N14: =(G14-M14)/M14 -> -0.0018573189
... A1304: 1302 | B1304: 46112 | C1304: 1000000 | D1304: 1353255.9 | E1304: 1579279.2 | F1304: 17183.977 | G1304: 1596463.1 | H1304: 596463.13 | I1304: 0.596463 | K1304: =(G1304-G1303) / G1303 -> 0.0071711351 | M1304: =MAX($G$2:G1304) -> 1679321.8 | N1304: =(G1304-M1304)/M1304 -> -0.049340572

Sheet URTH
A1: id | B1: symbol | C1: price_date | D1: open_price | E1: high_price | F1: low_price | G1: close_price | H1: volume | J1: daily return | L1: peak | M1: daily drawdaown
A2: 1494807 | B2: URTH | C2: 46134 | D2: 194.67 | E2: 195 | F2: 194.34 | G2: 194.92 | H2: 771500 | J2: =(G2-G3) / G3 -> 0.0084850993 | L2: =MAX(G2:$G$1259) -> 195.79 | M2: =(G2-L2) / L2 -> -0.0044435364
A3: 1494778 | B3: URTH | C3: 46133 | D3: 195.52 | E3: 195.66 | F3: 192.93 | G3: 193.28 | H3: 2488000 | J3: =(G3-G4) / G4 -> -0.011406066 | L3: =MAX(G3:$G$1259) -> 195.79 | M3: =(G3-L3) / L3 -> -0.012819858
A4: 1494749 | B4: URTH | C4: 46132 | D4: 195.21 | E4: 195.61 | F4: 194.61 | G4: 195.51 | H4: 2060600 | J4: =(G4-G5) / G5 -> -0.0014301037 | L4: =MAX(G4:$G$1259) -> 195.79 | M4: =(G4-L4) / L4 -> -0.0014301037
A5: 1494720 | B5: URTH | C5: 46129 | D5: 195.25 | E5: 196.48 | F5: 194.87 | G5: 195.79 | H5: 276800 | J5: =(G5-G6) / G6 -> 0.012462509 | L5: =MAX(G5:$G$1259) -> 195.79 | M5: =(G5-L5) / L5 -> 0
A6: 1494691 | B6: URTH | C6: 46128 | D6: 193.64 | E6: 193.75 | F6: 192.78 | G6: 193.38 | H6: 272600 | J6: =(G6-G7) / G7 -> 0.00025862515 | L6: =MAX(G6:$G$1259) -> 193.38 | M6: =(G6-L6) / L6 -> 0
A7: 1494662 | B7: URTH | C7: 46127 | D7: 192.21 | E7: 193.43 | F7: 191.89 | G7: 193.33 | H7: 1367100 | J7: =(G7-G8) / G8 -> 0.0069270833 | L7: =MAX(G7:$G$1259) -> 193.33 | M7: =(G7-L7) / L7 -> 0
A8: 1494633 | B8: URTH | C8: 46126 | D8: 190.76 | E8: 192.21 | F8: 190.74 | G8: 192 | H8: 1053600 | J8: =(G8-G9) / G9 -> 0.010579504 | L8: =MAX(G8:$G$1259) -> 192.37 | M8: =(G8-L8) / L8 -> -0.0019233768
A9: 1494604 | B9: URTH | C9: 46125 | D9: 187.58 | E9: 190.09 | F9: 187.37 | G9: 189.99 | H9: 752800 | J9: =(G9-G10) / G10 -> 0.0085465548 | L9: =MAX(G9:$G$1259) -> 192.37 | M9: =(G9-L9) / L9 -> -0.012371991
A10: 1494575 | B10: URTH | C10: 46122 | D10: 188.96 | E10: 189.19 | F10: 188.02 | G10: 188.38 | H10: 285200 | J10: =(G10-G11) / G11 -> 0.00010617966 | L10: =MAX(G10:$G$1259) -> 192.37 | M10: =(G10-L10) / L10 -> -0.02074128
A11: 1494546 | B11: URTH | C11: 46121 | D11: 187.11 | E11: 188.78 | F11: 186.7 | G11: 188.36 | H11: 618500 | J11: =(G11-G12) / G12 -> 0.0037301503 | L11: =MAX(G11:$G$1259) -> 192.37 | M11: =(G11-L11) / L11 -> -0.020845246
A12: 1494517 | B12: URTH | C12: 46120 | D12: 188.11 | E12: 188.54 | F12: 186.69 | G12: 187.66 | H12: 628300 | J12: =(G12-G13) / G13 -> 0.028443032 | L12: =MAX(G12:$G$1259) -> 192.37 | M12: =(G12-L12) / L12 -> -0.024484067
A13: 1494488 | B13: URTH | C13: 46119 | D13: 181.74 | E13: 182.55 | F13: 180.19 | G13: 182.47 | H13: 264100 | J13: =(G13-G14) / G14 -> 0.0041272287 | L13: =MAX(G13:$G$1259) -> 192.37 | M13: =(G13-L13) / L13 -> -0.051463326
... A1258: 1458297 | B1258: URTH | C1258: 44292 | D1258: 111.7294 | E1258: 112.1078 | F1258: 111.6001 | G1258: 111.8032 | H1258: 273800 | J1258: =(G1258-G1259) / G1259 -> 0.011186953 | L1258: =MAX(G1258:$G$1259) -> 111.8032 | M1258: =(G1258-L1258) / L1258 -> 0
A1259: 1458268 | B1259: URTH | C1259: 44287 | D1259: 109.994 | E1259: 110.6494 | F1259: 109.9294 | G1259: 110.5663 | H1259: 131900
A1260: 1458239 | B1260: URTH | C1260: 44286 | D1260: 109.0155 | E1260: 109.7448 | F1260: 109.0155 | G1260: 109.3755 | H1260: 232300
A1261: 1458210 | B1261: URTH | C1261: 44285 | D1261: 108.8124 | E1261: 109.1817 | F1261: 108.6278 | G1261: 108.9971 | H1261: 31000
A1262: 1458181 | B1262: URTH | C1262: 44284 | D1262: 108.9601 | E1262: 109.5047 | F1262: 108.5724 | G1262: 109.237 | H1262: 108200
A1263: 1458152 | B1263: URTH | C1263: 44281 | D1263: 108.4063 | E1263: 109.6617 | F1263: 108.1755 | G1263: 109.3847 | H1263: 108800
A1264: 1458123 | B1264: URTH | C1264: 44280 | D1264: 107.1417 | E1264: 108.157 | F1264: 106.5324 | G1264: 108.0278 | H1264: 157800
A1265: 1458094 | B1265: URTH | C1265: 44279 | D1265: 108.2678 | E1265: 108.6186 | F1265: 107.4094 | G1265: 107.4094 | H1265: 55600
A1266: 1458065 | B1266: URTH | C1266: 44278 | D1266: 108.7017 | E1266: 109.0155 | F1266: 107.8524 | G1266: 108.0001 | H1266: 81600
A1267: 1458036 | B1267: URTH | C1267: 44277 | D1267: 108.4801 | E1267: 109.514 | F1267: 108.4801 | G1267: 109.0155 | H1267: 295200
A1268: 1458007 | B1268: URTH | C1268: 44274 | D1268: 108.4524 | E1268: 108.8863 | F1268: 107.7232 | G1268: 108.5447 | H1268: 38300
A1269: 1457978 | B1269: URTH | C1269: 44273 | D1269: 109.2832 | E1269: 109.8463 | F1269: 108.2863 | G1269: 108.5078 | H1269: 85200
A1270: 1457949 | B1270: URTH | C1270: 44272 | D1270: 109.0801 | E1270: 110.1786 | F1270: 108.7386 | G1270: 110.0401 | H1270: 49600
... A2491: 1422466 | B2491: URTH | C2491: 42485 | D2491: 59.222 | E2491: 59.2636 | F2491: 58.9554 | G2491: 59.097 | H2491: 9300
